LICENSE
README.md
setup.cfg
setup.py
pyblas/__init__.py
pyblas/lsame.py
pyblas/util.py
pyblas/xerbla.py
pyblas/xerbla_array.py
pyblas.egg-info/PKG-INFO
pyblas.egg-info/SOURCES.txt
pyblas.egg-info/dependency_links.txt
pyblas.egg-info/requires.txt
pyblas.egg-info/top_level.txt
pyblas/level1/__init__.py
pyblas/level1/caxpy.py
pyblas/level1/ccopy.py
pyblas/level1/cdotc.py
pyblas/level1/cdotu.py
pyblas/level1/crotg.py
pyblas/level1/cscal.py
pyblas/level1/csrot.py
pyblas/level1/csscal.py
pyblas/level1/cswap.py
pyblas/level1/dasum.py
pyblas/level1/daxpy.py
pyblas/level1/dcabs1.py
pyblas/level1/dcopy.py
pyblas/level1/ddot.py
pyblas/level1/dnrm2.py
pyblas/level1/drot.py
pyblas/level1/drotg.py
pyblas/level1/drotm.py
pyblas/level1/drotmg.py
pyblas/level1/dscal.py
pyblas/level1/dsdot.py
pyblas/level1/dswap.py
pyblas/level1/dzasum.py
pyblas/level1/dznrm2.py
pyblas/level1/sasum.py
pyblas/level1/saxpy.py
pyblas/level1/scabs1.py
pyblas/level1/scasum.py
pyblas/level1/scnrm2.py
pyblas/level1/scopy.py
pyblas/level1/sdot.py
pyblas/level1/sdsdot.py
pyblas/level1/snrm2.py
pyblas/level1/srot.py
pyblas/level1/srotg.py
pyblas/level1/srotm.py
pyblas/level1/srotmg.py
pyblas/level1/sscal.py
pyblas/level1/sswap.py
pyblas/level1/zaxpy.py
pyblas/level1/zcopy.py
pyblas/level1/zdotc.py
pyblas/level1/zdotu.py
pyblas/level1/zdrot.py
pyblas/level1/zdscal.py
pyblas/level1/zrotg.py
pyblas/level1/zscal.py
pyblas/level1/zswap.py