Metadata-Version: 2.1
Name: pyblas
Version: 0.0.10
Summary: A python port of the netlib reference BLAS implementation.
Home-page: https://github.com/timleslie/pyblas
Author: Tim Leslie
Author-email: tim.leslie@gmail.com
License: BSD-3-Clause License
Project-URL: Bug Reports, https://github.com/timleslie/pyblas/issues
Project-URL: Source, https://github.com/timleslie/pyblas/
Keywords: numpy,blas,numerical computing
Platform: UNKNOWN
Classifier: Development Status :: 3 - Alpha
Classifier: Intended Audience :: Education
Classifier: Intended Audience :: Science/Research
Classifier: Intended Audience :: Developers
Classifier: License :: OSI Approved :: BSD License
Classifier: Programming Language :: Python :: 3
Classifier: Programming Language :: Python :: 3.6
Classifier: Programming Language :: Python :: 3.7
Classifier: Programming Language :: Python :: 3.8
Classifier: Programming Language :: Python :: 3.9
Classifier: Programming Language :: Python :: 3 :: Only
Requires-Python: >=3.6, <4
